ELSholdings/kenwoo/xls2ppt.py
ELSholdings/kenwoo/xls2ppt_pc.py
ELSholdings-3.0.0.dist-info/METADATA
ELSholdings-3.0.0.dist-info/WHEEL
ELSholdings-3.0.0.dist-info/top_level.txt
ELSholdings-3.0.0.dist-info/RECORD
