Metadata-Version: 2.1
Name: ELSholdings
Version: 3.0.0
Summary: Kenwoo project of ELS indexing
Author-email: HST <ye0077@naver.com>
Classifier: Programming Language :: Python :: 3
Classifier: License :: OSI Approved :: MIT License
Classifier: Operating System :: OS Independent
Requires-Python: >=3.8
